protobuf_grpc_distutils/__init__.py
protobuf_grpc_distutils/_version.py
protobuf_grpc_distutils/generate_grpc_py_protobufs.py
protobuf_grpc_distutils-0.1.5.dist-info/LICENSE
protobuf_grpc_distutils-0.1.5.dist-info/METADATA
protobuf_grpc_distutils-0.1.5.dist-info/WHEEL
protobuf_grpc_distutils-0.1.5.dist-info/entry_points.txt
protobuf_grpc_distutils-0.1.5.dist-info/top_level.txt
protobuf_grpc_distutils-0.1.5.dist-info/RECORD
