Metadata-Version: 2.1
Name: protobuf-grpc-distutils
Version: 0.1.5
Author: Shareef Jalloq
Author-email: shareef.jalloq@idexbiometrics.com
License: MIT
Project-URL: homepage, https://github.com/idex-biometrics/protobuf-grpc-distutils
Keywords: protobuf,grpc
Classifier: Programming Language :: Python :: 3
Classifier: License :: OSI Approved :: MIT License
Requires-Python: >=3.6
License-File: LICENSE
Requires-Dist: grpcio-tools
